py_s2s/__init__.py
py_s2s/s2s.py
py_s2s/s2s_client.py
py_s2s/s2s_connection_config.py
py_s2s-22.2.28.dist-info/LICENSE
py_s2s-22.2.28.dist-info/WHEEL
py_s2s-22.2.28.dist-info/METADATA
py_s2s-22.2.28.dist-info/RECORD
