Metadata-Version: 2.1
Name: py-s2s
Version: 22.2.28
Summary: Python service to service communication over rabbitmq ephemeral queues
Home-page: https://hivewire.co
License: Apache-2.0
Keywords: Service-to-Service,aio-pika,asyncio,rabbitmq,microservices
Author: Skyler Lewis
Author-email: skyler@hivewire.co
Requires-Python: >=3.8,<4.0
Classifier: License :: OSI Approved :: Apache Software License
Classifier: Programming Language :: Python :: 3
Classifier: Programming Language :: Python :: 3.10
Classifier: Programming Language :: Python :: 3.8
Classifier: Programming Language :: Python :: 3.9
Requires-Dist: aio-pika (>=7.1,<8.0)
Project-URL: Documentation, https://gitlab.com/hivewire/open-source/py-s2s/-/blob/master/README.md
Project-URL: Repository, https://gitlab.com/hivewire/open-source/py-s2s
